llama_index/py.typed
llama_index/vector_stores/duckdb/__init__.py
llama_index/vector_stores/duckdb/base.py
llama_index_vector_stores_duckdb-0.5.1.dist-info/METADATA
llama_index_vector_stores_duckdb-0.5.1.dist-info/WHEEL
llama_index_vector_stores_duckdb-0.5.1.dist-info/licenses/LICENSE
llama_index_vector_stores_duckdb-0.5.1.dist-info/RECORD
