Metadata-Version: 2.4
Name: llama-index-vector-stores-duckdb
Version: 0.5.1
Summary: llama-index vector_stores duckdb integration
Author-email: Adithya Krishnan <me@krishadi.com>, Bill Easton <williamseaston@gmail.com>
Maintainer: krish-adi
License-Expression: MIT
License-File: LICENSE
Requires-Python: <4.0,>=3.9
Requires-Dist: duckdb<1.4.0,>=0.10.1
Requires-Dist: llama-index-core<0.15,>=0.13.0
Requires-Dist: pyarrow>=20.0.0
